cx_wealth/__init__.py
cx_wealth/common.py
cx_wealth/dynamic_columns.py
cx_wealth/indexed_list_panel.py
cx_wealth/rich_types.py
cx_wealth/wealth_detail.py
cx_wealth/wealth_label.py
cx_wealth/wealth_help/__init__.py
cx_wealth/wealth_help/_action.py
cx_wealth/wealth_help/_group.py
cx_wealth/wealth_help/_node.py
cx_wealth/wealth_help/w_help.py
cx_wealth-0.1.0.3.dist-info/METADATA
cx_wealth-0.1.0.3.dist-info/WHEEL
cx_wealth-0.1.0.3.dist-info/entry_points.txt
cx_wealth-0.1.0.3.dist-info/RECORD
