Metadata-Version: 2.4
Name: cx-wealth
Version: 0.1.0.3
Summary: A lib of CLI gadgets extended from rich.
Author-email: xiii_1991 <xiii_1991@163.com>
Requires-Python: >=3.12
Requires-Dist: rich>=14.0.0
